musicbrainzapi/__init__.py
musicbrainzapi/api.py
musicbrainzapi/enums.py
musicbrainzapi/exceptions.py
musicbrainzapi/models.py
musicbrainzapi/py.typed
musicbrainzapi-0.1.1.dist-info/METADATA
musicbrainzapi-0.1.1.dist-info/WHEEL
musicbrainzapi-0.1.1.dist-info/RECORD
