Metadata-Version: 2.1
Name: musicbrainzapi
Version: 0.1.1
Summary: 
Home-page: https://github.com/Dr-Blank/musicbrainzapi
License: MIT
Author: Dr-Blank
Author-email: 64108942+Dr-Blank@users.noreply.github.com
Requires-Python: >=3.8.10,<4.0.0
Classifier: License :: OSI Approved :: MIT License
Classifier: Programming Language :: Python :: 3
Classifier: Programming Language :: Python :: 3.9
Classifier: Programming Language :: Python :: 3.10
Classifier: Programming Language :: Python :: 3.11
Classifier: Programming Language :: Python :: 3.12
Requires-Dist: beautifulsoup4 (>=4.12.2,<5.0.0)
Requires-Dist: musicbrainzngs (>=0.7.1,<0.8.0)
Requires-Dist: requests (>=2,<3)
Requires-Dist: requests-ratelimiter (>=0.4.2,<0.5.0)
Project-URL: Repository, https://github.com/Dr-Blank/musicbrainzapi
